extLog/__init__.py
extLog-20230712.2.dist-info/METADATA
extLog-20230712.2.dist-info/WHEEL
extLog-20230712.2.dist-info/top_level.txt
extLog-20230712.2.dist-info/RECORD
