Metadata-Version: 2.1
Name: extLog
Version: 20230712.2
Summary: 简易日志记录器
Author: yleaf
